dataset/duration.json.xz
dataset/multithread.json.xz
dataset/svtav1_vs_rav1e.json.xz
dataset/x264_vs_openh264.json.xz
mendevi/__init__.py
mendevi/__main__.py
mendevi/cmd.py
mendevi/convert.py
mendevi/decode.py
mendevi/encode.py
mendevi/encoder.py
mendevi/exceptions.py
mendevi/probe.py
mendevi/utils.py
mendevi/cli/__init__.py
mendevi/cli/decode.py
mendevi/cli/doc.py
mendevi/cli/download.py
mendevi/cli/encode.py
mendevi/cli/g5k.py
mendevi/cli/json.py
mendevi/cli/merge.py
mendevi/cli/parse.py
mendevi/cli/plot.py
mendevi/cli/prepare.py
mendevi/cli/probe.py
mendevi/cli/test.py
mendevi/cli/version.py
mendevi/cst/__init__.py
mendevi/cst/encoders.py
mendevi/cst/labels.py
mendevi/cst/plot.py
mendevi/cst/profiles.py
mendevi/database/__init__.py
mendevi/database/complete.py
mendevi/database/create.py
mendevi/database/extract.py
mendevi/database/meta.py
mendevi/database/serialize.py
mendevi/download/__init__.py
mendevi/download/decapsulation.py
mendevi/download/decompress.py
mendevi/download/torrent_finder.py
mendevi/download/transmission.py
mendevi/measures/__init__.py
mendevi/measures/context.py
mendevi/measures/g5kpower.py
mendevi/measures/gpu.py
mendevi/measures/psutil.py
mendevi/measures/rapl.py
mendevi/models/__init__.py
mendevi/models/base.py
mendevi/models/power_cores.py
mendevi/plot/__init__.py
mendevi/plot/printer.py
mendevi/plot/tools.py
mendevi/testing/__init__.py
mendevi/testing/coding_style.py
mendevi/testing/install.py
mendevi/testing/run.py
mendevi/testing/tests/__init__.py
mendevi/testing/tests/encode_cmd.py
mendevi/testing/tests/extractor.py
mendevi/testing/tests/integrity.py
mendevi-1.3.0.dist-info/licenses/LICENSE
mendevi-1.3.0.dist-info/METADATA
mendevi-1.3.0.dist-info/WHEEL
mendevi-1.3.0.dist-info/entry_points.txt
mendevi-1.3.0.dist-info/top_level.txt
mendevi-1.3.0.dist-info/RECORD
