Metadata-Version: 2.4
Name: mendevi
Version: 1.3.0
Summary: Video encoding and decoding measures.
Author-email: "Robin RICHARD (robinechuca)" <robin.richard@inria.fr>
Maintainer-email: "Robin RICHARD (robinechuca)" <robin.richard@inria.fr>
License:                     GNU AFFERO GENERAL PUBLIC LICENSE
Project-URL: Documentation, https://mendevi.readthedocs.io/latest
Project-URL: Repository, https://gitlab.inria.fr/rrichard/mendevi
Keywords: av1,consumption,energy,h264,h265,h266,measure,power,psnr,ssim,video decoding,video encoding,video,vmaf,vp9,wattmeter
Classifier: Development Status :: 5 - Production/Stable
Classifier: Intended Audience :: Education
Classifier: Intended Audience :: Science/Research
Classifier: Natural Language :: English
Classifier: Operating System :: POSIX :: Linux
Classifier: Programming Language :: Python :: 3
Classifier: Programming Language :: SQL
Classifier: Topic :: Database :: Database Engines/Servers
Classifier: Topic :: File Formats :: JSON
Classifier: Topic :: Multimedia :: Video :: Conversion
Requires-Python: <3.15,>=3.12
License-File: LICENSE
Requires-Dist: click
Requires-Dist: context_verbose
Requires-Dist: cutcutcodec
Requires-Dist: flufl.lock
Requires-Dist: levenshtein
Requires-Dist: matplotlib
Requires-Dist: networkx
Requires-Dist: numpy
Requires-Dist: nvidia-ml-py
Requires-Dist: orjson
Requires-Dist: psutil
Requires-Dist: pygments
Requires-Dist: requests
Requires-Dist: tqdm
Requires-Dist: unidecode
Provides-Extra: doc
Requires-Dist: furo; extra == "doc"
Requires-Dist: mathjax; extra == "doc"
Requires-Dist: recommonmark; extra == "doc"
Requires-Dist: ruff; extra == "doc"
Requires-Dist: sphinx; extra == "doc"
Requires-Dist: sphinx-copybutton; extra == "doc"
Requires-Dist: sphinx-inline-tabs; extra == "doc"
Requires-Dist: sphinxcontrib-video; extra == "doc"
Requires-Dist: sphinxext-opengraph; extra == "doc"
Provides-Extra: test
Requires-Dist: enoslib; extra == "test"
Requires-Dist: pytest; extra == "test"
Requires-Dist: ruff; extra == "test"
Dynamic: license-file
